dubboclient/__init__.py
dubboclient/core.py
dubboclient-1.0.2.dist-info/METADATA
dubboclient-1.0.2.dist-info/WHEEL
dubboclient-1.0.2.dist-info/top_level.txt
dubboclient-1.0.2.dist-info/RECORD
