Metadata-Version: 2.1
Name: dubboclient
Version: 1.0.2
Summary: A client tool for testing the Dubbo API
Home-page: https://github.com/likgjava/dubboclient
Author: outman
Author-email: likg.java@163.com
License: MIT Licence
Keywords: pip,dubboclient,DubboClient,dubbo
Platform: any
